NSDQ/AssetCLS.py
NSDQ/DataCLS.py
NSDQ/OptionsCLS.py
NSDQ/Utils.py
NSDQ/__init__.py
NSDQ-0.3.2.dist-info/METADATA
NSDQ-0.3.2.dist-info/WHEEL
NSDQ-0.3.2.dist-info/top_level.txt
NSDQ-0.3.2.dist-info/RECORD
