Metadata-Version: 2.1
Name: NSDQ
Version: 0.3.2
Summary: UNKNOWN
Home-page: UNKNOWN
License: UNKNOWN
Platform: UNKNOWN
Requires-Dist: seaborn
Requires-Dist: requests
Requires-Dist: pandas
Requires-Dist: py-vollib
Requires-Dist: py-vollib-vectorized
Requires-Dist: scipy
Requires-Dist: matplotlib
Requires-Dist: numpy
